tomorrow3/__init__.py
tomorrow3/tomorrow3.py
tomorrow3-1.2.2.dist-info/METADATA
tomorrow3-1.2.2.dist-info/WHEEL
tomorrow3-1.2.2.dist-info/top_level.txt
tomorrow3-1.2.2.dist-info/RECORD
