Metadata-Version: 2.1
Name: tomorrow3
Version: 1.2.2
Summary: simplified tomorrow for python3
Home-page: https://github.com/dflupu/tomorrow3
Author: Daniel Lupu
Author-email: lupu.daniel.f@gmail.com
License: MIT License (See LICENSE)
Platform: UNKNOWN
